rst_previewer/__init__.py
rst_previewer/app.py
rst_previewer/main.py
rst_previewer-0.1.2.dist-info/METADATA
rst_previewer-0.1.2.dist-info/WHEEL
rst_previewer-0.1.2.dist-info/entry_points.txt
rst_previewer-0.1.2.dist-info/licenses/LICENSE
rst_previewer-0.1.2.dist-info/RECORD
