Metadata-Version: 2.4
Name: rst-previewer
Version: 0.1.2
Summary: A modern CLI and web-based viewer for reStructuredText files.
Project-URL: Bug Tracker, https://github.com/rohanmohapatra/rst-previewer/issues
Project-URL: Homepage, https://github.com/rohanmohapatra/rst-previewer
Author-email: rohanmohapatra <rohanironcrest14@gmail.com>
License-File: LICENSE
Classifier: License :: OSI Approved :: MIT License
Classifier: Operating System :: OS Independent
Classifier: Programming Language :: Python :: 3
Classifier: Topic :: Text Editors :: Documentation
Classifier: Topic :: Utilities
Requires-Python: >=3.10
Requires-Dist: docutils>=0.21
Requires-Dist: gradio>=4.0.0
Requires-Dist: termcolor>=2.4.0
Requires-Dist: typer[all]>=0.9.0
